spotisyaspy/__init__.py
spotisyaspy/_version.py
spotisyaspy/spotisyaspy.py
spotisyaspy-0.2.1.dist-info/LICENSE
spotisyaspy-0.2.1.dist-info/METADATA
spotisyaspy-0.2.1.dist-info/WHEEL
spotisyaspy-0.2.1.dist-info/top_level.txt
spotisyaspy-0.2.1.dist-info/RECORD
