Metadata-Version: 2.1
Name: spotisyaspy
Version: 0.2.1
Summary: SpotIsyAsPy - An object-oriented wrapper for the Spotify API.
Author-email: Pethő Gergely <pagstudium@gmail.com>
License: MIT License
Project-URL: Homepage, https://github.com/gpetho/spotisyaspy
Project-URL: Bug Tracker, https://github.com/gpetho/spotisyaspy/issues
Classifier: Programming Language :: Python :: 3
Classifier: Operating System :: OS Independent
Requires-Python: >=3.8
License-File: LICENSE
Requires-Dist: requests>=2.31.0
Requires-Dist: flask>=2.3.2
Requires-Dist: tqdm>=4.66.1
